cazenga_ui/__init__.py
cazenga_ui/apps.py
cazenga_ui/cli.py
cazenga_ui/management/__init__.py
cazenga_ui/management/commands/__init__.py
cazenga_ui/management/commands/cazenga.py
cazenga_ui/management/commands/cazenga_setup.py
cazenga_ui/management/commands/ui.py
cazenga_ui/static_source/css/components/components.css
cazenga_ui/static_source/css/theme/blue/styles.css
cazenga_ui/static_source/css/theme/blue/theme.css
cazenga_ui/static_source/css/theme/default/theme.css
cazenga_ui/static_source/css/theme/green/theme.css
cazenga_ui/static_source/css/theme/orange/theme.css
cazenga_ui/static_source/css/theme/red/theme.css
cazenga_ui/static_source/css/theme/rose/theme.css
cazenga_ui/static_source/css/theme/violet/theme.css
cazenga_ui/static_source/css/theme/yellow/theme.css
cazenga_ui/static_source/js/sidebar-highlight.js
cazenga_ui/static_source/js/spa-debug.js
cazenga_ui/static_source/js/spa-intelligent.js
cazenga_ui/static_source/js/spa-simple.js
cazenga_ui/static_source/js/spa.js
cazenga_ui/templates_source/base.html
cazenga_ui/templates_source/icons/accessibility.svg
cazenga_ui/templates_source/icons/activity-log.svg
cazenga_ui/templates_source/icons/align-baseline.svg
cazenga_ui/templates_source/icons/align-bottom.svg
cazenga_ui/templates_source/icons/align-center-horizontally.svg
cazenga_ui/templates_source/icons/align-center-vertically.svg
cazenga_ui/templates_source/icons/align-center.svg
cazenga_ui/templates_source/icons/align-end.svg
cazenga_ui/templates_source/icons/align-horizontal-centers.svg
cazenga_ui/templates_source/icons/align-left.svg
cazenga_ui/templates_source/icons/align-right.svg
cazenga_ui/templates_source/icons/align-start.svg
cazenga_ui/templates_source/icons/align-stretch.svg
cazenga_ui/templates_source/icons/align-top.svg
cazenga_ui/templates_source/icons/align-vertical-centers.svg
cazenga_ui/templates_source/icons/all-sides.svg
cazenga_ui/templates_source/icons/angle.svg
cazenga_ui/templates_source/icons/archive.svg
django_cazenga_ui-0.1.6.dist-info/licenses/LICENSE.txt
django_cazenga_ui-0.1.6.dist-info/METADATA
django_cazenga_ui-0.1.6.dist-info/WHEEL
django_cazenga_ui-0.1.6.dist-info/entry_points.txt
django_cazenga_ui-0.1.6.dist-info/top_level.txt
django_cazenga_ui-0.1.6.dist-info/RECORD
