Metadata-Version: 2.4
Name: django-cazenga-ui
Version: 0.1.6
Summary: Biblioteca moderna de componentes UI para Django usando Tailwind CSS v4 e Alpine.js
Author-email: Comunidade Cazenga <contato@cazenga.com>
License: MIT
Project-URL: Homepage, https://github.com/cazenga/django-cazenga-ui
Project-URL: Documentation, https://django-cazenga-ui.readthedocs.io
Project-URL: Repository, https://github.com/cazenga/django-cazenga-ui
Project-URL: Issues, https://github.com/cazenga/django-cazenga-ui/issues
Project-URL: Changelog, https://github.com/cazenga/django-cazenga-ui/blob/main/CHANGELOG.md
Keywords: django,tailwind,ui,components,alpine,shadcn
Classifier: Development Status :: 4 - Beta
Classifier: Environment :: Web Environment
Classifier: Framework :: Django
Classifier: Framework :: Django :: 3.2
Classifier: Framework :: Django :: 4.0
Classifier: Framework :: Django :: 4.1
Classifier: Framework :: Django :: 4.2
Classifier: Framework :: Django :: 5.0
Classifier: Framework :: Django :: 5.1
Classifier: Intended Audience :: Developers
Classifier: License :: OSI Approved :: MIT License
Classifier: Operating System :: OS Independent
Classifier: Programming Language :: Python
Classifier: Programming Language :: Python :: 3
Classifier: Programming Language :: Python :: 3 :: Only
Classifier: Programming Language :: Python :: 3.8
Classifier: Programming Language :: Python :: 3.9
Classifier: Programming Language :: Python :: 3.10
Classifier: Programming Language :: Python :: 3.11
Classifier: Programming Language :: Python :: 3.12
Classifier: Topic :: Internet :: WWW/HTTP
Classifier: Topic :: Internet :: WWW/HTTP :: Dynamic Content
Classifier: Topic :: Software Development :: Libraries :: Application Frameworks
Classifier: Topic :: Software Development :: Libraries :: Python Modules
Requires-Python: >=3.8
License-File: LICENSE.txt
Requires-Dist: Django>=3.2
Requires-Dist: django-tailwind[reload]
Requires-Dist: django-browser-reload
Requires-Dist: django-mathfilters
Provides-Extra: tailwind
Provides-Extra: dev
Requires-Dist: pytest; extra == "dev"
Requires-Dist: pytest-django; extra == "dev"
Requires-Dist: black; extra == "dev"
Requires-Dist: isort; extra == "dev"
Requires-Dist: flake8; extra == "dev"
Requires-Dist: mypy; extra == "dev"
Requires-Dist: django-stubs[compatible-mypy]; extra == "dev"
Provides-Extra: test
Requires-Dist: pytest; extra == "test"
Requires-Dist: pytest-django; extra == "test"
Requires-Dist: pytest-cov; extra == "test"
Dynamic: license-file
